{"id": "269193336", "public_at": "1193018176", "last_modified": "1718268569", "site_category": "\u5b97\u6559\u8d85\u81ea\u7136", "site_category_id": "41", "sub_site_category": "\u672a\u9078\u64c7", "sub_site_category_id": "-1", "category": "\u8a2d\u7acb\u5b97\u65e8\u8207\u7ba1\u7406\u8aaa\u660e", "category_id": "3270884", "link": "https://mickey1124.pixnet.net/blog/post/269193336", "status": "2", "is_top": "0", "is_nl2br": "0", "comment_perm": "1", "comment_hidden": "0", "title": "\u767c\u554f\uff1a\u7528\u300e\u5c0f\u5c0f\u7f8a\u300f\u4e09\u5b57\uff0c\u7b97\u4e0d\u7b97\u5177\u9ad4\u7f72\u540d\uff1f", "thumb": "https://imageproxy.pimg.tw/zoomcrop?width=90&height=90&url=https%3A%2F%2Ffront.pixfs.net%2Fimages%2Farticle_default_image.png", "cover": "", "hits": {"total": 53, "daily": 0}, "info": {"trackbacks_count": 0, "comments_count": 18, "shareds_count": 0, "hit": 53}, "hit_uri": "https://counter.pixplug.in/count.php?timestamp=1718270142&random=1733789089&check=2153200693&no_timeout=2&data[blogarticle]=%7B%22blogid%22%3A%227468761%22%2C%22articleid%22%3A%22269193336%22%2C%22no_timeout%22%3A2%7D", "sns": {"twitter": null, "facebook": null, "plurk": null}, "tags": [], "tags_string": "", "user": {"name": "mickey1124", "display_name": "\u5c0f\u5c0f\u7f8a", "avatar": "https://s1.pimg.tw/avatar/mickey1124/0/0/resize/90x0.png?v=", "cavatar": "https://s1.pimg.tw/avatar/mickey1124/0/0/zoomcrop/90x90.png?v=", "link": "https://mickey1124.pixnet.net", "member_uniqid": "588475c1c633d5d0e6", "is_vip": false, "has_ad": false, "avatar_role_id": 10, "avatar_role_url": "https://s.pixfs.net/common/icons/planet--icon-10.png"}, "body": "  <div>\u9019\u662fPETER\u7db2\u53cb\u767c\u51fa\u7684\u7591\u554f\u3002\u6709\u8208\u8da3\u7684\u5144\u59ca\uff0c\u4e0d\u59a8\u53ef\u4ee5\u5404\u81ea\u767c\u8868\u770b\u6cd5\u3002</div>\n\n<div>\uff5e\uff5e\uff5e\uff5e</div>\n\n<div>\u4f60\u597d:</div>\n\n<div>\u5c0f\u5c0f\u7f8a\u611f\u89ba\u9084\u4e0d\u5920\u5177\u9ad4\u7f72\u540d,</div>\n\n<div>&nbsp;</div>\n\n<div>\u6211\u8a8d\u70ba\u7c3d\u540d\u8ca0\u8cac,\u597d\u58de\u90fd\u8ca0\u8cac,</div>\n\n<div>\u9084\u662f\u6bd4\u8f03\u597d\u7684,</div>\n\n<div>&nbsp;</div>\n\n<div>Posted by PETER at 2007\u5e7410\u670819\u65e5 16:29</div>\n\n<div>\uff5e\uff5e\uff5e\uff5e\uff5e</div>\n\n<div>&nbsp;</div>\n\n<div>&nbsp;</div>\n\n<div>&nbsp;</div>\n\n<div>&nbsp;</div>\n\n<div>\uff5e\uff5e\uff5e\uff5e</div>\n\n<div>PETER\u60a8\u597d\uff1a</div>\n\n<div>\u6211\u4e0d\u592a\u78ba\u5b9a\u60a8\u7684\u610f\u601d\uff0c\u6240\u4ee5\u8981\u6f84\u6e05\u4e00\u4e0b\uff1a</div>\n\n<div>\u60a8\u8aaa\u300e\u5c0f\u5c0f\u7f8a\u611f\u89ba\u9084\u4e0d\u5920\u5177\u9ad4\u7f72\u540d\u300f\uff0c</div>\n\n<div>\u610f\u601d\u662f\u8aaa\u6211\u9019\u88e1\u9762\u7684\u6587\u7ae0\uff0c\u61c9\u8a72\u7528\u6211\u771f\u5be6\u59d3\u540d\u4f86\u767c\u8868\uff0c\u624d\u6bd4\u8f03\u5408\u9069\uff0c</div>\n\n<div>\u662f\u9019\u6a23\u55ce\uff1f</div>\n\n<div>&nbsp;</div>\n\n<div>Posted by \u5c0f\u5c0f\u7f8a at 2007\u5e7410\u670821\u65e5 18:38</div>\n\n<div>\uff5e\uff5e\uff5e\uff5e\uff5e</div>\n\n<div>&nbsp;</div>\n\n<div>&nbsp;</div>\n\n<div>&nbsp;</div>\n\n<div>&nbsp;</div>\n\n<div>\uff5e\uff5e\uff5e\uff5e</div>\n\n<div>\u5c0f\u5c0f\u7f8a_\u662f\u4e00\u500b\u4eba,\u9084\u662f\u4e00\u7fa4\u4eba?</div>\n\n<div>&nbsp;</div>\n\n<div>\u56e0\u70ba\u6211\u5c31\u662f\u6c6a\u5f1f\u5144,</div>\n\n<div>\u57fa\u7763\u5f92 3% ,\u59d3\u6c6a\u7684\u53ef\u80fd\u4e0d\u5230 1%,</div>\n\n<div>\u842c\u5206\u4e4b\u4e09\u7684\u6a5f\u7387,</div>\n\n<div>&nbsp;</div>\n\n<div>\u4eca\u5929\u7684\u7559\u8a00\u88e1,\u90fd\u6709\u51fa\u73fe \"\u6211\",</div>\n\n<div>\u90a3\u8868\u793a\u5c0f\u5c0f\u7f8a_\u662f\u4e00\u500b\u4eba,</div>\n\n<div>\u6bd4\u8f03\u597d,</div>\n\n<div>&nbsp;</div>\n\n<div>\u6211\u8a8d\u70ba,</div>\n\n<div>\u65e2\u7136\u662f\u56de\u61c9\u5510\u7267\u5e2b\u7684\u547c\u53ec,</div>\n\n<div>\u5be6\u5728\u5149\u660e\u6b63\u5927,</div>\n\n<div>\u4e0d\u7528\u50cf\u85cf\u93e1\u4eba,\u5e36\u982d\u7f69,\u5957\u7d72\u896a,(\u53cd\u800c\u795e\u79d8,)</div>\n\n<div>\u8b93\u4eba\u4e0d\u77e5\u9053\u4f60\u662f\u8ab0,</div>\n\n<div>\u4e0a\u5e1d\u8aaa:\u6211\u662f,</div>\n\n<div>\u8036\u7a4c\u8aaa:\u6211\u662f,</div>\n\n<div>&nbsp;</div>\n\n<div>\u6bd4\u5982\u5510\u7267\u5e2b\u4f48\u9053\u5718,</div>\n\n<div>\u4e5f\u662f\u7c3d\u540d\u8ca0\u8cac,</div>\n\n<div>\u4e0d\u7136,\u53ef\u4ee5\u53d6\u540d\"\u5370\u5c3c\u67d0\u50b3\u9053\u4eba\u4f48\u9053\u5718\",</div>\n\n<div>\u9019\u9ebc\u5bb3\u7f9e\u554a?\u9019\u9ebc\u6b79\u52e2\u554a?</div>\n\n<div>&nbsp;</div>\n\n<div>_____________________________</div>\n\n<div>\u7576\u7136,\u9019\u500b\u7db2\u7ad9\u8ffd\u6c42\u4fe1\u4ef0\u6b63\u78ba,</div>\n\n<div>\u9867\u4e00\u500b\u7db2\u7ad9\u662f\u5f88\u7d2f\u7684,</div>\n\n<div>\u6211\u4e0d\u662f\u4f86\u627e\u9ebb\u7169\u7684,</div>\n\n<div>\u8b1d\u8b1d!</div>\n\n<div>&nbsp;</div>\n\n<div>Posted by PETER at 2007\u5e7410\u670822\u65e5 03:22</div>\n\n<div>\uff5e\uff5e\uff5e\uff5e\uff5e</div>\n\n<div>&nbsp;</div>\n\n<div>&nbsp;</div>\n\n<div>&nbsp;</div>\n\n<div>&nbsp;</div>\n\n<div>\uff5e\uff5e\uff5e\uff5e</div>\n\n<div>\u771f\u5be6\u59d3\u540d,</div>\n\n<div>\u7528\u771f\u5be6\u59d3\u540d\u5f88\u597d,</div>\n\n<div>\u4f46\u5982\u679c\u76ee\u524d\u6709\u96e3\u8655,\u5c31\u7b97\u4e86,</div>\n\n<div>\u6bd4\u5982\u7db2\u8def\u4e0a,\u6709\u9a37\u64fe,\u99ed\u5ba2,</div>\n\n<div>\u90a3\u5c31\u6bd4\u8f03\u9ebb\u7169,</div>\n\n<div>&nbsp;</div>\n\n<div>\u81f3\u5c11\u4eca\u5929,</div>\n\n<div>\u6211\u77e5\u9053 \u5c0f\u5c0f\u7f8a\u61c9\u8a72\u662f\u6307\u67d0\u4e00\u4f4d\u7279\u5b9a\u7684\u4eba,</div>\n\n<div>&nbsp;</div>\n\n<div>Posted by PETER at 2007\u5e7410\u670822\u65e5 03:32</div>\n\n<div>\uff5e\uff5e\uff5e\uff5e\uff5e</div>\n\n<div>&nbsp;</div>\n\n<div>&nbsp;</div>\n\n<div>&nbsp;</div>\n\n<div>&nbsp;</div>\n\n<div>\uff5e\uff5e\uff5e\uff5e\uff5e</div>\n\n<div>\u5c0f\u5c0f\u7f8a \u65bc 2007/10/22 17:13 \u516c\u958b\u56de\u8986</div>\n\n<div>&nbsp;</div>\n\n<div>\u5c0d\u65bcPETER\u7db2\u53cb\u7684\u89c0\u5ff5\uff0c\u6211\u505a\u4e00\u500b\u6574\u7406\uff1a</div>\n\n<div>1.\u5c0f\u5c0f\u7f8a\u611f\u89ba\u9084\u4e0d\u5920\u5177\u9ad4\u7f72\u540d,\u6211\u8a8d\u70ba\u7c3d\u540d\u8ca0\u8cac,\u597d\u58de\u90fd\u8ca0\u8cac,\u9084\u662f\u6bd4\u8f03\u597d\u7684,</div>\n\n<div>2.\u4e0d\u7528\u50cf\u85cf\u93e1\u4eba,\u5e36\u982d\u7f69,\u5957\u7d72\u896a,(\u53cd\u800c\u795e\u79d8,)\u8b93\u4eba\u4e0d\u77e5\u9053\u4f60\u662f\u8ab0,</div>\n\n<div>&nbsp;</div>\n\n<div>&nbsp;</div>\n\n<div>\u9996\u5148\uff0c\u6211\u4e5f\u60f3\u8acb\u554fPETER\u7db2\u53cb\uff1a</div>\n\n<div>1.<span style=\"white-space:pre\"> </span>\u55ae\u55ae\u5728\u9019\u7db2\u7ad9\uff0c\u60a8\u5df2\u7d93\u7528\u904e\u591a\u5c11\u7a2e\u7b46\u540d\u4f86\u767c\u8a00\u4e86\uff1f</div>\n\n<div>\u55ae\u55ae\u60a8\u81ea\u5df1\u627f\u8a8d\u7684\uff0c\u5c31\u5df2\u7d93\u5169\u500b\u7b46\u540d\u4e86\uff0c\u4e0d\u662f\u55ce\uff1f</div>\n\n<div>2.<span style=\"white-space:pre\"> </span>\u70ba\u4ec0\u9ebc\u60a8\u4f86\u9019\u88e1\uff0c\u4e0d\u80af\u7528\u771f\u5be6\u59d3\u540d\u4f86\u767c\u8a00\u5462\uff1f</div>\n\n<div>\u300e\u7c3d\u540d\u8ca0\u8cac,\u597d\u58de\u90fd\u8ca0\u8cac\u300f\uff0c\u4e0d\u662f\u55ce\uff1f</div>\n\n<div>\u300e\u4e0d\u7528\u50cf\u85cf\u93e1\u4eba,\u5e36\u982d\u7f69,\u5957\u7d72\u896a,(\u53cd\u800c\u795e\u79d8,)\u8b93\u4eba\u4e0d\u77e5\u9053\u4f60\u662f\u8ab0\u300f\uff0c\u4e0d\u662f\u55ce\uff1f</div>\n\n<div>\u65e2\u7136\u60a8\u7528\u9019\u6a23\u7684\u6a19\u6e96\u4f86\u8981\u6c42\u6211\uff0c</div>\n\n<div>\u90a3\u9ebc\uff0c\u60a8\u7d93\u5f97\u8d77\u81ea\u5df1\u7528\u540c\u6a23\u7684\u6a19\u6e96\u4f86\u8981\u6c42\u81ea\u5df1\u55ce\uff1f</div>\n\n<div>\u5225\u5fd8\u4e86\uff0c\u8056\u7d93\u56b4\u53b2\u7981\u6b62\u96d9\u91cd\u6a19\u6e96\uff0c\u4e0d\u51c6\u5169\u6a23\u6cd5\u78bc\uff0c\u9019\u662f\u5927\u7f6a\u3002</div>\n\n<div>\u60a8\u60f3\u7528\u4f86\u8981\u6c42\u5225\u4eba\u7684\u6a19\u6e96\uff0c\u81ea\u5df1\u5c31\u8a72\u5168\u90e8\u90fd\u8981\u505a\u5230\uff0c</div>\n\n<div>\u5426\u5247\u5c31\u662f\u5bec\u4ee5\u5f85\u5df1\u3001\u56b4\u4ee5\u5f8b\u4eba\uff0c\u89f8\u72af\u5927\u7f6a\u3002</div>\n\n<div>\u300e\u5169\u6a23\u7684\u6cd5\u78bc\u70ba\u8036\u548c\u83ef\u6240\u618e\u60e1\u300f\uff08\u7bb420\uff1a23\uff09</div>\n\n<div>\u300e\u4f60\u5728\u751a\u9ebc\u4e8b\u4e0a\u8ad6\u65b7\u4eba\uff0c\u5c31\u5728\u751a\u9ebc\u4e8b\u4e0a\u5b9a\u81ea\u5df1\u7684\u7f6a\uff1b</div>\n\n<div>\u56e0\u4f60\u9019\u8ad6\u65b7\u4eba\u7684\uff0c\u81ea\u5df1\u6240\u884c\u537b\u548c\u5225\u4eba\u4e00\u6a23\u300f\uff08\u7f852\uff1a1\uff09</div>\n\n<div>\u300e\u4f60\u8ad6\u65b7\u884c\u9019\u6a23\u4e8b\u7684\u4eba\uff0c\u81ea\u5df1\u6240\u884c\u7684\u537b\u548c\u5225\u4eba\u4e00\u6a23\uff0c</div>\n\n<div>\u4f60\u4ee5\u70ba\u80fd\u9003\u812b\u795e\u7684\u5be9\u5224\u55ce\uff1f\u300f\uff08\u7f852\uff1a3\uff09</div>\n\n<div>&nbsp;</div>\n\n<div>&nbsp;</div>\n\n<div>\u5510\u7267\u5e2b\u81ea\u5df1\u5e38\u8b1b\u300e\u4e0d\u8981\u628a\u7d55\u5c0d\u7576\u76f8\u5c0d\uff0c\u4e5f\u4e0d\u8981\u628a\u76f8\u5c0d\u7576\u7d55\u5c0d\u300f\uff0c</div>\n\n<div>\u56e0\u6b64\uff0c\u63a5\u4e0b\u4f86\uff0c\u6211\u9084\u8981\u8acb\u6559PETER\u7db2\u53cb\uff1a</div>\n\n<div>1.\u300e\u7528\u771f\u5be6\u59d3\u540d\u767c\u8a00\uff0c\u4ee5\u793a\u8ca0\u8cac\u300f\uff0c\u9019\u6a23\u7684\u89c0\u5ff5\uff0c</div>\n\n<div>\u662f\u7d55\u5c0d\u7684\u771f\u7406\uff0c\u9084\u662f\u5c6c\u65bc\u76f8\u5c0d\u7684\u9818\u57df\uff1f</div>\n\n<div>2.<span style=\"white-space:pre\"> </span>\u6c92\u7528\u771f\u5be6\u59d3\u540d\u767c\u8a00\uff0c\u6709\u6c92\u6709\u72af\u7f6a\uff1f</div>\n\n<div>\u5982\u679c\u6709\u72af\u7f6a\uff0c\u72af\u8056\u7d93\u54ea\u689d\u7f6a\uff1f</div>\n\n<div>\u5982\u679c\u6c92\u72af\u7f6a\uff0c\u90a3\u9ebc\uff0c\u9019\u8868\u793a\u60a8\u662f\u5728\u7528\u500b\u4eba\u4e3b\u89c0\u60f3\u6cd5\u4f86\u8981\u6c42\u5225\u4eba\u5949\u884c\uff0c</div>\n\n<div>\u9019\u53c8\u8a72\u7576\u4f55\u7f6a\uff1f</div>\n\n<div>&nbsp;</div>\n\n<div>&nbsp;</div>\n\n<div>\u518d\u56de\u904e\u4f86\uff0c\u8ac7\u5230\u5c0f\u5c0f\u7f8a\u90e8\u5206\u3002</div>\n\n<div>\u6211\u7528\u5c0f\u5c0f\u7f8a\u7576\u7b46\u540d\uff0c\u6709\u6c92\u6709\u9055\u53cd\u60a8\u81ea\u5df1\u63d0\u51fa\u7684\u89c0\u5ff5\uff1f\uff1a</div>\n\n<div>1.\u7c3d\u540d\u8ca0\u8cac,\u597d\u58de\u90fd\u8ca0\u8cac</div>\n\n<div>2.\u4e0d\u7528\u50cf\u85cf\u93e1\u4eba,\u5e36\u982d\u7f69,\u5957\u7d72\u896a,(\u53cd\u800c\u795e\u79d8,)\u8b93\u4eba\u4e0d\u77e5\u9053\u4f60\u662f\u8ab0</div>\n\n<div>&nbsp;</div>\n\n<div>&nbsp;</div>\n\n<div>\u5176\u5be6\uff0c\u6211\u53ef\u4ee5\u8b1b\uff1a</div>\n\n<div>\u591a\u6578\u7db2\u53cb\u4e00\u9ede\u4e5f\u4e0d\u89ba\u5f97\u6211\u7528\u5c0f\u5c0f\u7f8a\u7576\u7b46\u540d\uff0c\u6709\u9055\u53cd\u60a8\u81ea\u5df1\u6240\u63d0\u51fa\u7684\u89c0\u5ff5\uff1b</div>\n\n<div>\u53cd\u800c\u662f\u60a8\u81ea\u5df1\u7528\u597d\u5e7e\u7a2e\u7b46\u540d\u5728\u6211\u5011\u9019\u88e1\u767c\u8a00\uff0c\u624d\u662f\u81ea\u5df1\u6c92\u505a\u5230\u81ea\u5df1\u7684\u8981\u6c42\u3002</div>\n\n<div>\u800c\u60a8\u8981\u6c42\u6211\u8981\u505a\u5230\u7684\u300e\u7528\u771f\u5be6\u59d3\u540d\u300f\uff0c\u60a8\u81ea\u5df1\u6839\u672c\u4e5f\u6c92\u505a\u5230\u3002</div>\n\n<div>&nbsp;</div>\n\n<div>&nbsp;</div>\n\n<div>\u6211\u53ef\u4ee5\u9ad4\u8ad2\u5f88\u591a\u80a2\u9ad4\u7684\u8edf\u5f31\uff0c\u4e0d\u7ba1\u662f\u8eab\u9ad4\u4e0a\u3001\u7cbe\u795e\u4e0a\u3001\u5fc3\u9748\u4e0a\u7684\u3002</div>\n\n<div>\u4f46\u662f\uff0c\u9019\u4e0d\u8868\u793a\u6211\u6703\u7e31\u5bb9\u3002</div>\n\n<div>\u4e0d\u904e\uff0c\u6211\u7684\u8a9e\u6c23\u6216\u8a31\u56b4\u53b2\uff0c</div>\n\n<div>\u4f46\u662f\uff0c\u6211\u5fc3\u4e2d\u4e26\u7121\u61a4\u6012\uff0c\u66f4\u6c92\u6709\u6068\u3002</div>\n\n<div>\u6211\u53ea\u76fc\u60a8\u767c\u8a00\u4e4b\u524d\uff0c\u80fd\u6709\u6240\u7bc0\u5236\uff0c\u80fd\u591a\u4e9b\u8003\u616e\u3002</div>\n\n<div>\u82e5\u6709\u7591\u554f\uff0c\u767c\u554f\u4fbf\u662f\uff0c\u8acb\u5148\u4e0d\u8981\u52a0\u4e0a\u8a55\u65b7\u3002</div>\n\n<div>&nbsp;</div>\n\n<div>&nbsp;</div>\n\n<div>\u6211\u5c0d\u65bc\u60a8\u7684\u90e8\u5206\uff0c\u5c31\u8b1b\u5230\u9019\u88e1\u3002</div>\n\n<div>&nbsp;</div>\n\n<div>&nbsp;</div>\n\n<div>&nbsp;</div>\n\n<div>&nbsp;</div>\n\n<div>\u4ee5\u4e0b\uff0c\u662f\u6211\u500b\u4eba\u611f\u8a00\uff0c\u8981\u8b1b\u7d66\u6211\u5011\u9019\u88e1\u5ee3\u5927\u7684\u5f1f\u5144\u59ca\u59b9\u807d\u7684\u3002</div>\n\n<div>&nbsp;</div>\n\n<div>&nbsp;</div>\n\n<div>\u6211\u76f8\u4fe1\uff0c\u5c0f\u5f1f\u6211\u5beb\u7684\u6587\u7ae0\uff0c\u53ef\u80fd\u9084\u6709\u4e00\u4e9b\u4e9b\u53ef\u4ee5\u9707\u64bc\u4eba\u5fc3\u7684\u529b\u91cf\u3002</div>\n\n<div>\u6211\u4e0d\u662f\u8aaa\u81ea\u5df1\u6587\u7ae0\u6709\u591a\u4e86\u4e0d\u8d77\uff0c</div>\n\n<div>\u4e0d\uff01\u6211\u7684\u6587\u7ae0\u4e00\u9ede\u90fd\u6c92\u6709\u4e86\u4e0d\u8d77\u3002</div>\n\n<div>\u4f46\u662f\uff0c\u6211\u81ea\u5df1\u767c\u73fe\uff0c\u8056\u9748\u900f\u904e\u6211\u9019\u4e9b\u6587\u5b57\u5728\u505a\u5de5\uff0c</div>\n\n<div>\u800c\u9019\u6a23\u7684\u767c\u73fe\uff0c\u61c9\u8a72\u4e5f\u4e0d\u662f\u53ea\u6709\u6211\u81ea\u5df1\u767c\u73fe\uff0c\u800c\u662f\u6709\u5f88\u591a\u5f1f\u5144\u59ca\u59b9\u4e5f\u767c\u73fe\u3002</div>\n\n<div>&nbsp;</div>\n\n<div>&nbsp;</div>\n\n<div>\u6211\u4e0d\u662f\u4e00\u500b\u795e\u8056\u7684\u4eba\uff0c\u6211\u662f\u4e00\u500b\u4f9d\u7136\u6703\u72af\u7f6a\u72af\u932f\u7684\u4fd7\u4eba\u3002</div>\n\n<div>\u4e0a\u5e1d\u7528\u6211\uff0c\u4e26\u4e0d\u662f\u56e0\u70ba\u6211\u7684\u53e3\u624d\u3001\u6211\u7684\u6587\u7b46\u3001\u6211\u7684\u667a\u6167\u3001\u6211\u7684\u3001\u3001\u3001\u3002</div>\n\n<div>\u6211\u81ea\u5df1\u89ba\u5f97\uff0c\u4e0a\u5e1d\u7528\u6211\uff0c\u53ea\u662f\u56e0\u70ba\uff1a</div>\n\n<div>1.<span style=\"white-space:pre\"> </span>\u6211\u5728\u7942\u9762\u524d\u6240\u5b58\u7684\u4e7e\u6de8\u7684\u5fc3\u3002</div>\n\n<div>\u662f\u771f\u5fc3\u70ba\u4e86\u4e0a\u5e1d\u7684\u69ae\u8000\uff0c\u800c\u975e\u70ba\u4e86\u6211\u500b\u4eba\u7684\u69ae\u8000\u3002</div>\n\n<div>2.<span style=\"white-space:pre\"> </span>\u6211\u80fd\u5beb\u7684\uff0c\u53ea\u6709\u6211\u81ea\u5df1\u76f8\u4fe1\u3001\u81ea\u5df1\u505a\u5230\u3001\u6216\u662f\u5f88\u8a8d\u771f\u5728\u52aa\u529b\u8ffd\u6c42\u7684\u3002</div>\n\n<div>\u6211\u505a\u4e0d\u5230\u7684\uff0c\u6211\u6c92\u81c9\u5beb\u3001\u4e0d\u6562\u5beb\u3001\u4e5f\u4e0d\u9858\u5beb\u3002</div>\n\n<div>\u6211\u505a\u4e0d\u5230\u7684\u6771\u897f\uff0c\u54ea\u6562\u8981\u6c42\u6211\u7684\u5f1f\u5144\u5011\u505a\u5230\u5462\uff1f</div>\n\n<div>&nbsp;</div>\n\n<div>&nbsp;</div>\n\n<div>\u6210\u8056\u7684\u8def\u4e0a\uff0c\u662f\u4f55\u7b49\u7684\u8271\u96e3\u53c8\u9059\u9060\u3002</div>\n\n<div>\u6211\u8dcc\u5012\u904e\u3001\u6d41\u6dda\u904e\u3001\u6d41\u8840\u904e\u3002</div>\n\n<div>\u6211\u5f9e\u4f86\u5c31\u4e0d\u662f\u7528\u300e\u6211\u505a\u5230\uff0c\u800c\u4f60\u6c92\u505a\u5230\uff0c\u6240\u4ee5\u6211\u9ad8\u4f60\u4e00\u7b49\u300f\u7684\u614b\u5ea6\u4f86\u5beb\u6587\u7ae0\uff0c</div>\n\n<div>\u6211\u7684\u614b\u5ea6\u662f\uff1a</div>\n\n<div>\u300e\u6211\u9019\u9ebc\u8edf\u5f31\u7684\u4eba\uff0c\u7adf\u7136\u53ef\u4ee5\u505a\u5230\uff0c</div>\n\n<div>\u90a3\u9ebc\uff0c\u4f60\u53ea\u8981\u9858\u610f\u9760\u8457\u4e3b\uff0c\u6709\u4e00\u5929\uff0c\u4f60\u4e00\u5b9a\u4e5f\u53ef\u4ee5\u505a\u5230\u300f</div>\n\n<div>&nbsp;</div>\n\n<div>&nbsp;</div>\n\n<div>\u6211\u7684\u6587\u7ae0\uff0c\u5404\u7a2e\u98a8\u683c\u90fd\u6709\u3002</div>\n\n<div>\u6709\u5f88\u56b4\u53b2\u7684\uff0c\u6709\u53cd\u8af7\u7684\uff0c\u6709\u6eab\u67d4\u7684\uff0c\u6709\u52f8\u52c9\u3001\u6709\u9f13\u52f5\u3001\u3001\u3001\u3002</div>\n\n<div>\u5982\u679c\u9858\u610f\u7528\u5fc3\u770b\uff0c\u61c9\u8a72\u53ef\u4ee5\u767c\u73fe\u6211\u7684\u5fc3\u3002</div>\n\n<div>&nbsp;</div>\n\n<div>&nbsp;</div>\n\n<div>\u70ba\u4ec0\u9ebc\u7db2\u8def\u4e0a\u57fa\u7763\u6559\u6587\u7ae0\u90a3\u9ebc\u591a\uff0c</div>\n\n<div>\u4f46\u662f\uff0c\u771f\u80fd\u8b93\u4eba\u807d\u5230\u4e0a\u5e1d\u900f\u904e\u9019\u4e9b\u6587\u7ae0\u8b1b\u8a71\u7684\u5f88\u5c11\uff1f</div>\n\n<div>\u6709\u5f88\u591a\uff0c\u53ea\u662f\u5728\u5531\u9ad8\u8abf\uff08\u9019\u592a\u591a\u4e86\uff09\uff1b</div>\n\n<div>\u6709\u5f88\u591a\uff0c\u4e0d\u662f\u771f\u7684\u61f7\u8457\u5f88\u4e7e\u6de8\u7684\u5fc3\uff1b</div>\n\n<div>\u6709\u5f88\u591a\uff0c\u53ea\u662f\u500b\u4eba\u7684\u5462\u5583\u8207\u56c8\u8a9e\uff1b</div>\n\n<div>\u6709\u5f88\u591a\uff0c\u53ea\u662f\u73a9\u73a9\uff0c\u4e0d\u662f\u7528\u5fc3\u4f86\u4e8b\u5949\u4e3b\u3001\u3001\u3001\u3001\u3002</div>\n\n<div>\u6c92\u6709\u529b\u91cf\u7684\u6587\u5b57\uff0c\u5982\u4f55\u80fd\u5e6b\u52a9\u4eba\uff1f</div>\n\n<div>\u6c92\u6709\u751f\u547d\u5728\u88e1\u9762\u7684\u6587\u5b57\uff0c\u90a3\u80fd\u6fc0\u52f5\u4eba\u8ddf\u96a8\u4e3b\uff1f</div>\n\n<div>&nbsp;</div>\n\n<div>&nbsp;</div>\n\n<div>\u7db2\u8def\u662f\u4e00\u500b\u865b\u64ec\u7684\u4e16\u754c\uff0c\u548c\u6b63\u5e38\u793e\u6703\u6709\u76f8\u4f3c\u4e4b\u8655\uff0c\u4e5f\u6709\u76f8\u7570\u4e4b\u8655\u3002</div>\n\n<div>\u6211\u5011\u7684\u540d\u5b57\uff0c\u662f\u7236\u6bcd\u7d66\u7684\uff0c\u9019\u662f\u6211\u5011\u5728\u793e\u6703\u4e0a\u7684\u8eab\u4efd\u3002</div>\n\n<div>\u4f46\u662f\uff0c\u55ae\u55ae\u540d\u5b57\uff0c\u5c31\u80fd\u8b49\u5be6\u6211\u5011\u8eab\u4efd\u55ce\uff1f</div>\n\n<div>\u7576\u7136\u4e0d\u662f\uff01</div>\n\n<div>\u5426\u5247\uff0c\u70ba\u4f55\u9084\u9700\u7167\u7247\uff1f\u9084\u9700\u8eab\u4efd\u8b49\u865f\u78bc\uff1f\u751a\u81f3\u9084\u9700\u8840\u578b\u3001DNA\uff1f</div>\n\n<div>\u8981\u8b49\u5be6\u4e00\u500b\u4eba\u7684\u8eab\u4efd\uff0c\u8aaa\u7c21\u55ae\u5f88\u7c21\u55ae\uff0c\u8aaa\u96e3\u4e5f\u5f88\u96e3\u3002</div>\n\n<div>&nbsp;</div>\n\n<div>&nbsp;</div>\n\n<div>\u5510\u5d07\u69ae\u7267\u5e2b\u5728\u53f0\u7063\u8b1b\u9053\uff0c\u4ed6\u7528\u4ee5\u8b58\u5225\u7684\u540d\u5b57\u662f\u300e\u5510\u5d07\u69ae\u300f\uff1b</div>\n\n<div>\u4ed6\u5728\u82f1\u8a9e\u7cfb\u570b\u5bb6\u8b1b\u9053\u6642\uff0c\u7528\u4ee5\u8b58\u5225\u7684\u540d\u5b57\u53ef\u80fd\u5c31\u8b8a\u6210\u300eStephen Tong\u300f\u3002</div>\n\n<div>&nbsp;</div>\n\n<div>&nbsp;</div>\n\n<div>\u4e00\u5b9a\u8981\u771f\u5be6\u59d3\u540d\uff0c\u624d\u80fd\u8b93\u5225\u4eba\u8b58\u5225\u55ce\uff1f</div>\n\n<div>\u7576\u6211\u53bb\u6b63\u5f0f\u6703\u8b70\u8b1b\u9053\u3001\u5728\u6559\u6703\u8b1b\u9053\u6642\uff0c\u6211\u7576\u7136\u7528\u771f\u5be6\u59d3\u540d\u3002</div>\n\n<div>\u56e0\u70ba\uff0c\u90a3\u88e1\u6c92\u4ec0\u9ebc\u4eba\u8a8d\u8b58\u300e\u5c0f\u5c0f\u7f8a\u300f\u3002</div>\n\n<div>\u4f46\u662f\uff0c\u7576\u6211\u5728\u5c0f\u5c0f\u7f8a\u5712\u5730\u7a81\u7136\u7528\u6211\u771f\u5be6\u59d3\u540d\u767c\u8a00\uff0c</div>\n\n<div>\u5927\u5bb6\u6703\u77e5\u9053\u90a3\u5c31\u662f\u6211\u672c\u4eba\u55ce\uff1f</div>\n\n<div>&nbsp;</div>\n\n<div>&nbsp;</div>\n\n<div>\u539f\u8ad2\u6211\u5982\u6b64\u8aaa\uff1a</div>\n\n<div>\u4e0d\u8981\u592a\u819a\u6dfa\uff01</div>\n\n<div>\u4e8b\u5be6\u4e0a\uff0c\u4e0d\u7ba1\u5728\u54ea\u4e00\u500b\u7db2\u7ad9\uff0c\u5927\u5bb6\u90fd\u53ef\u4ee5\u7528\u4e00\u500b\u7b46\u540d\u4f86\u767c\u8a00\u3002</div>\n\n<div>\u53ea\u8981\u7528\u540c\u6a23\u7684\u7b46\u540d\u767c\u8a00\u4e45\u4e86\uff0c</div>\n\n<div>\u5927\u5bb6\u5c31\u6703\u77e5\u9053\u4f60\u9019\u500b\u4eba\u4e00\u8cab\u7684\u8a00\u8ad6\u8207\u7acb\u5834\u3001</div>\n\n<div>\u96a8\u6642\u53ef\u4ee5\u641c\u5c0b\u4f60\u5728\u9019\u7db2\u7ad9\u516c\u958b\u7684\u8a00\u8ad6\u3002</div>\n\n<div>\u8acb\u554f\uff0c\u9019\u6a23\u7684\u4f7f\u7528\u7b46\u540d\u7684\u65b9\u5f0f\uff0c\u6703\u4e0d\u5920\u8ca0\u8cac\u55ce\uff1f</div>\n\n<div>&nbsp;</div>\n\n<div>&nbsp;</div>\n\n<div>\u7576\u7136\uff0c\u5982\u679c\u5728\u4e00\u500b\u7db2\u7ad9\u88e1\uff0c\u540c\u4e00\u4eba\u7528\u591a\u7a2e\u7b46\u540d\uff0c</div>\n\n<div>\u5225\u4eba\u7576\u7136\u5c31\u96e3\u4ee5\u8fa8\u8a8d\u51fa\u9019\u662f\u8ab0\u7684\u8a00\u8ad6\u3002</div>\n\n<div>\u4f46\u662f\uff0c\u6211\u672c\u4eba\u4e0d\u9019\u6a23\u505a\uff1b</div>\n\n<div>\u53ef\u662f\uff0c\u6211\u4e5f\u4e0d\u6703\u89ba\u5f97\u4eba\u4eba\u90fd\u4e0d\u80fd\u5982\u6b64\u505a\u3002</div>\n\n<div>\u7db2\u8def\u672c\u4f86\u5c31\u662f\u865b\u64ec\u3001\u53ef\u4ee5\u96b1\u533f\u7684\u3002</div>\n\n<div>&nbsp;</div>\n\n<div>&nbsp;</div>\n\n<div>\u5f9e\u6211\u5728\u7db2\u8def\u4e0a\u57fa\u7763\u6559\u5340\u57df\u767c\u8a00\u958b\u59cb\uff0c\u6211\u7684\u7b46\u540d\u5c31\u662f\u300e\u5c0f\u5c0f\u7f8a\u300f\u3002</div>\n\n<div>\u5225\u4eba\u53ef\u4e0d\u53ef\u4ee5\u7528\u9019\u7b46\u540d\uff1f</div>\n\n<div>\u7576\u7136\u53ef\u4ee5\uff01</div>\n\n<div>\u5982\u4f55\u8b58\u5225\uff1f\u53ea\u80fd\u770b\u500b\u4eba\u529f\u529b\u4e86\u3002</div>\n\n<div>\u4e00\u822c\u800c\u8a00\uff0c\u6211\u9084\u6c92\u770b\u904e\u8ab0\u6587\u7ae0\u98a8\u683c\u548c\u6211\u4e00\u6a23\u7684\u3002</div>\n\n<div>\u6211\u6c92\u8fa6\u6cd5\u53bb\u8b49\u660e\u54ea\u4e00\u500b\u7db2\u7ad9\u7684\u5c0f\u5c0f\u7f8a\u662f\u6211\u672c\u4eba\uff0c</div>\n\n<div>\u6b63\u5982\u6211\u5011\u4e5f\u7121\u6cd5\u8b49\u5be6\u8ab0\u662f\u300e\u6dd1\u82ac\u300f\uff08\u83dc\u5e02\u5834\u540d\uff0c\u5f88\u591a\u4eba\u90fd\u53d6\u9019\u540d\u5b57\uff09\u3002</div>\n\n<div>\u6211\u53ea\u80fd\u8aaa\uff0c\u5728\u6211\u9019\u5712\u5730\u88e1\uff0c\u5c0f\u5c0f\u7f8a\u5c31\u662f\u6211\uff0c\u6211\u5c31\u662f\u5c0f\u5c0f\u7f8a\u3002</div>\n\n<div>&nbsp;</div>\n\n<div>&nbsp;</div>\n\n<div>\u7528\u771f\u5be6\u59d3\u540d\uff0c\u5c31\u6bd4\u8f03\u80fd\u8ca0\u8cac\uff1f</div>\n\n<div>\u5176\u5be6\uff0c\u771f\u8981\u8ca0\u8cac\uff0c\u4e0d\u9700\u4f7f\u7528\u771f\u5be6\u59d3\u540d\u4e5f\u80fd\u8ca0\u8cac\uff1b</div>\n\n<div>\u4e0d\u60f3\u8ca0\u8cac\uff0c\u5373\u4f7f\u7528\u771f\u5be6\u59d3\u540d\u4e00\u6a23\u4e5f\u80fd\u812b\u8cac\u3002</div>\n\n<div>\u96e3\u9053\uff0c\u6211\u5011\u61c9\u8a72\u8981\u6211\u5011\u9019\u7db2\u7ad9\u88e1\u6bcf\u4e00\u4f4d\u767c\u8a00\u7684\u4eba\uff0c</div>\n\n<div>\u90fd\u8981\u7528\u6b63\u5f0f\u540d\u5b57\u4f86\u767c\u8a00\uff0c\u624d\u53eb\u8ca0\u8cac\uff1f</div>\n\n<div>\u5176\u5be6\uff0c\u60f3\u7528\u771f\u5be6\u59d3\u540d\uff0c\u96a8\u6642\u53ef\u4ee5\u7528\uff1b</div>\n\n<div>\u4f46\u662f\uff0c\u8981\u6c42\u4eba\u4eba\u7528\u771f\u5be6\u59d3\u540d\u4f86\u7db2\u8def\u767c\u8a00\uff0c\u9019\u5c31\u4e0d\u5c0d\u4e86\u3002</div>\n\n<div>&nbsp;</div>\n\n<div>&nbsp;</div>\n\n<div>\u81ea\u5df1\u60f3\u505a\u7684\u4e8b\uff0c\u53ea\u8981\u4e0d\u9055\u53cd\u8056\u7d93\uff0c\u81ea\u5df1\u6191\u8457\u81ea\u5df1\u7684\u9818\u53d7\u8207\u4fe1\u5fc3\u53bb\u505a\u3002</div>\n\n<div>\u81ea\u5df1\u60f3\u505a\u7684\u4e8b\uff0c\u6c92\u6709\u660e\u78ba\u8056\u7d93\u4f9d\u64da\uff0c\u5c31\u8981\u6c42\u5927\u5bb6\u90fd\u8981\u7167\u81ea\u5df1\u60f3\u6cd5\u53bb\u505a\uff0c</div>\n\n<div>\u9019\u662f\u4e0d\u5c0a\u91cd\u80a2\u9ad4\u7684\u8868\u73fe\u3002</div>\n\n<div>\u300e\u4f60\u6709\u4fe1\u5fc3\uff0c\u5c31\u7576\u5728\u795e\u9762\u524d\u5b88\u8457\u3002</div>\n\n<div>\u4eba\u5728\u81ea\u5df1\u4ee5\u70ba\u53ef\u884c\u7684\u4e8b\u4e0a\u80fd\u4e0d\u81ea\u8cac\uff0c\u5c31\u6709\u798f\u4e86\u3002</div>\n\n<div>\u82e5\u6709\u7591\u5fc3\u800c\u5403\u7684\uff0c\u5c31\u5fc5\u6709\u7f6a\uff0c\u56e0\u70ba\u4ed6\u5403\u4e0d\u662f\u51fa\u65bc\u4fe1\u5fc3\u3002</div>\n\n<div>\u51e1\u4e0d\u51fa\u65bc\u4fe1\u5fc3\u7684\u90fd\u662f\u7f6a\u300f\uff08\u7f8514\uff1a22-23\uff09</div>\n\n<div>\u300e\u5b88\u65e5\u7684\u4eba\u662f\u70ba\u4e3b\u5b88\u7684\uff1b\u5403\u7684\u4eba\u662f\u70ba\u4e3b\u5403\u7684\uff0c\u56e0\u4ed6\u611f\u8b1d\u795e\uff1b</div>\n\n<div>\u4e0d\u5403\u7684\u4eba\u662f\u70ba\u4e3b\u4e0d\u5403\u7684\uff0c\u4e5f\u611f\u8b1d\u795e\u300f\uff08\u7f8514\uff1a6\uff09</div>\n\n<div>&nbsp;</div>\n\n<div>&nbsp;</div>\n\n<div>\u7db2\u8def\u662f\u771f\u5be6\u6559\u6703\u55ce\uff1f</div>\n\n<div>\u7db2\u8def\u662f\u771f\u5be6\u793e\u6703\u55ce\uff1f</div>\n\n<div>\u7576\u6211\u5011\u5728\u7db2\u8def\u4e0a\u7528\u771f\u5be6\u59d3\u540d\u767c\u8a00\uff0c\u6709\u4ec0\u9ebc\u597d\u8655\u5462\uff1f\u6709\u4ec0\u9ebc\u58de\u8655\u5462\uff1f</div>\n\n<div>\u4e0d\u7528\u771f\u5be6\u59d3\u540d\uff0c\u5c31\u8868\u793a\u81ea\u5df1\u4e0d\u6562\u8ca0\u6587\u8cac\u55ce\uff1f</div>\n\n<div>\u4f7f\u7528\u771f\u5be6\u59d3\u540d\uff0c\u5c31\u8868\u793a\u81ea\u5df1\u6bd4\u8f03\u795e\u8056\u55ce\uff1f</div>\n\n<div>&nbsp;</div>\n\n<div>&nbsp;</div>\n\n<div>\u77e5\u9053\u5c0f\u5c0f\u7f8a\u5230\u5e95\u771f\u5be6\u59d3\u540d\u662f\u4ec0\u9ebc\uff0c\u5c0d\u5927\u5bb6\u6709\u4ec0\u9ebc\u597d\u8655\u5462\uff1f</div>\n\n<div>\u53ef\u4ee5\u4f7f\u5927\u5bb6\u66f4\u8a8d\u8b58\u4e0a\u5e1d\uff1f</div>\n\n<div>\u53ef\u4ee5\u66f4\u69ae\u795e\u76ca\u4eba\uff1f</div>\n\n<div>\u6211\u4eca\u5929\u5728\u7db2\u8def\u4e0a\u7684\u6587\u5b57\uff0c\u7576\u6211\u7b46\u540d\u63db\u6210\u63db\u6210\u5c0f\u5c0f\u8c6c\uff0c</div>\n\n<div>\u6703\u5c0d\u6211\u6240\u8981\u50b3\u8b1b\u7684\u771f\u7406\u6709\u5f71\u97ff\u55ce\uff1f</div>\n\n<div>\u5927\u5bb6\u662f\u4f86\u8ddf\u96a8\u5c0f\u5c0f\u7f8a\uff0c\u9084\u662f\u8981\u8ddf\u96a8\u771f\u7406\uff1f</div>\n\n<div>\u5c0f\u5c0f\u7f8a\u8b1b\u932f\u6642\uff0c\u5927\u5bb6\u4e5f\u8981\u7167\u55ae\u5168\u6536\u55ce\uff1f</div>\n\n<div>\u4e0d\u8981\u7ba1\u5c0f\u5c0f\u7f8a\u662f\u8ab0\uff0c\u591a\u5c07\u6ce8\u610f\u529b\u653e\u5728\u5c0f\u5c0f\u7f8a\u50b3\u8b1b\u7684\u6771\u897f\u4e0a\u9762\u5427\uff1f</div>\n\n<div>\u5c07\u597d\u5947\u5fc3\u62ff\u4f86\u5206\u6790\u5c0f\u5c0f\u7f8a\uff0c</div>\n\n<div>\u9084\u4e0d\u5982\u5c07\u6642\u9593\u62ff\u4f86\u4e00\u53e5\u4e00\u53e5\u67e5\u8003\u5c0f\u5c0f\u7f8a\u6587\u7ae0\u88e1\u63d0\u4f9b\u7684\u7d93\u6587\u3002</div>\n\n<div>\u5c0f\u5c0f\u7f8a\u4e0d\u80fd\u63d0\u4f9b\u6c38\u751f\uff0c\u771f\u7406\u624d\u80fd\u63d0\u4f9b\u6c38\u751f\u3002</div>\n\n<div>&nbsp;</div>\n\n<div>&nbsp;</div>\n\n<div>\u7db2\u8def\u4e16\u754c\uff0c\u865b\u865b\u5be6\u5be6\u3002</div>\n\n<div>\u6211\u5011\u6839\u672c\u7121\u6cd5\u4e00\u4e00\u53bb\u8b49\u5be6\uff0c\u4e5f\u7121\u6cd5\u4e00\u4e00\u53bb\u6f84\u6e05\uff0c</div>\n\n<div>\u90a3\u771f\u662f\u6709\u5920\u6d6a\u8cbb\u6642\u9593\u3002</div>\n\n<div>\u771f\u7684\uff0c\u76e1\u91cf\u628a\u6642\u9593\u62ff\u4f86\u8a8d\u8b58\u771f\u7406\uff0c\u6bd4\u8f03\u6709\u610f\u7fa9\u3002</div>\n\n<div>\u5c0f\u5c0f\u7f8a\u771f\u5be6\u59d3\u540d\u662f\u4ec0\u9ebc\uff1f</div>\n\n<div>\u5c0f\u5c0f\u7f8a\u4f4f\u54ea\u88e1\uff1f</div>\n\n<div>\u5c0f\u5c0f\u7f8a\u9577\u4ec0\u9ebc\u6a23\u5b50\uff1f\u3001\u3001\u3001</div>\n\n<div>\u9019\u7a2e\u679d\u5fae\u672b\u7bc0\u7684\u554f\u984c\uff0c\u6211\u4fdd\u8b49\u6709\u4e00\u5929\u90fd\u6703\u544a\u8a34\u5927\u5bb6\u2026\u2026\u2026\u2026\u2026\u2026\u2026</div>\n\n<div>\u5929\u4e0a\u898b\u9762\u6642\uff0c\u6709\u6c38\u9060\u4e5f\u82b1\u4e0d\u5b8c\u7684\u6642\u9593\uff0c\u53ef\u4ee5\u4f86\u804a\u9019\u4e9b\u4e8b\u3002</div>\n\n<div>\u4f46\u9084\u5728\u5730\u4e0a\u6642\uff0c\u5c0f\u5c0f\u7f8a\u53d7\u547c\u53ec\uff0c\u4e0d\u662f\u4f86\u8b1b\u9019\u4e9b\u6771\u897f\uff0c\u800c\u662f\u4f86\u50b3\u8b1b\u771f\u7406\u3002</div>\n\n<div>\u5c0f\u5c0f\u7f8a\u8b1b\u7684\u771f\u7406\uff0c\u90fd\u7528\u5c0f\u5c0f\u7f8a\u7b46\u540d\u3002</div>\n\n<div>\u6211\u8b1b\u7684\uff0c\u6211\u7d55\u5c0d\u8ca0\u8cac\uff0c\u7d55\u5c0d\u627f\u8a8d\uff1b</div>\n\n<div>\u6211\u6c92\u8b1b\u7684\uff0c\u4e0d\u5e72\u6211\u7684\u4e8b\u3002</div>\n\n<div>\u6211\u4e0d\u559c\u6b61\u4eba\u5bb6\u6a21\u4eff\u6211\u7684\u7b46\u540d\uff0c\u751a\u81f3\u5192\u7528\u6211\u7b46\u540d\uff0c\u4f46\u6211\u6c92\u6709\u6b0a\u529b\u7981\u6b62\u3002</div>\n\n<div>\uff08\u6709\u4eba\u5192\u7528\u6211\u7b46\u540d\u53bb\u5225\u7684\u5730\u65b9\u6417\u86cb\uff0c\u90a3\u4e0d\u662f\u6211\u5e79\u7684\uff0c\u4f46\u6211\u7121\u6b0a\u529b\u5236\u6b62\uff09</div>\n\n<div>\u500b\u4eba\u5b58\u5fc3\uff0c\u90fd\u5c07\u5728\u4e0a\u5e1d\u9762\u524d\u9673\u660e\u3002</div>\n\n<div>\u662f\u51fa\u65bc\u4e7e\u6de8\u7684\u5fc3\u4f86\u670d\u4e8b\u795e\uff0c</div>\n\n<div>\u9084\u662f\u51fa\u65bc\u79c1\u617e\u4f86\u670d\u4e8b\u795e\uff0c</div>\n\n<div>\u6709\u4e00\u5929\uff0c\u4e0a\u5e1d\u90fd\u5c07\u5be9\u5224\u3002</div>\n\n<div>&nbsp;</div>\n\n<div>&nbsp;</div>\n\n<div>\u8b1b\u4e00\u4e0b\u6211\u70ba\u4ec0\u9ebc\u53d6\u9019\u7b46\u540d\u597d\u4e86\u3002</div>\n\n<div>\u6211\u89ba\u5f97\u81ea\u5df1\u7f6a\u5b7d\u6df1\u91cd\uff0c\u9023\u7a31\u81ea\u5df1\u70ba\u4e3b\u7684\u5c0f\u7f8a\u90fd\u4e0d\u914d\u3002</div>\n\n<div>\u6211\u53ea\u662f\u90a3\u4e00\u767e\u96bb\u7f8a\u88e1\u9762\uff0c\u6700\u4e0d\u4e56\u7684\u4e00\u96bb\u3002</div>\n\n<div>\u5176\u4ed6\u4e5d\u5341\u4e5d\u96bb\u90fd\u4e56\u4e56\u5728\u7f8a\u5708\u88e1\uff0c\u4f46\u6211\u537b\u662f\u96e2\u5bb6\u9060\u9060\u3002</div>\n\n<div>\u662f\u611b\u6211\u7684\u4e3b\uff0c\u6d41\u8840\u88ab\u834a\u68d8\u6240\u523a\uff0c\u4e0a\u5c71\u4e0b\u6d77\u3001\u5230\u6df1\u6df1\u7684\u5c71\u8c37\u88e1\uff0c</div>\n\n<div>\u5c07\u6211\u9019\u96bb\u5feb\u6454\u6b7b\u7684\u4e0d\u4e56\u7f8a\u5e36\u56de\u5bb6\u3002</div>\n\n<div>\u6211\u9019\u6a23\u7684\u4e00\u96bb\u7f8a\uff0c\u6709\u4ec0\u9ebc\u8cc7\u683c\u7a31\u81ea\u5df1\u70ba\u4e3b\u5c0f\u7f8a\uff1f</div>\n\n<div>\u6211\u662f\u7f8a\u5708\u88e1\uff0c\u6700\u4e0d\u8d77\u773c\u3001\u6700\u5fae\u4e0d\u8db3\u9053\u3001</div>\n\n<div>\u9023\u8209\u76ee\u671b\u5929\u90fd\u4e0d\u6562\uff0c\u53ea\u6562\u8aaa\u300e\u4e3b\u554a\u3001\u53ef\u6190\u6211\u9019\u7f6a\u4eba\u300f\u7684\u4e00\u96bb\u7f8a\u3002</div>\n\n<div>\u6240\u4ee5\uff0c\u6211\u53eb\u5c0f\u5c0f\u7f8a\uff0c\u4ee5\u793a\u81ea\u5df1\u662f\u4f55\u7b49\u4e0d\u914d\u3002</div>\n\n<div>\u5728\u793e\u6703\u4e0a\uff0c\u6211\u64c1\u6709\u5d07\u9ad8\u7684\u793e\u6703\u5730\u4f4d\uff0c\u4ee5\u53ca\u773e\u4eba\u7a31\u7fa8\u7684\u8a31\u591a\u6771\u897f\u3002</div>\n\n<div>\u4f46\u5728\u4e3b\u88e1\uff0c\u6211\u6df1\u77e5\u81ea\u5df1\u662f\u4f55\u7b49\u4e0d\u914d\uff0c\u4e16\u4e0a\u4e00\u5207\u69ae\u83ef\u5bcc\u8cb4\u90fd\u4e0d\u904e\u662f\u7cde\u571f\uff0c</div>\n\n<div>\u800c\u6211\u53ea\u662f\u87f2\u3001\u53ea\u662f\u7cde\u571f\u4e4b\u4eba\u800c\u5df2\u3002</div>\n\n<div>\u662f\u795e\u7684\u6069\u5178\uff0c\u80fd\u8b93\u6211\u6709\u6a5f\u6703\u670d\u4e8b\u7942\u3002</div>\n\n<div>\u6bcf\u6b21\u8b1b\u5230\u9019\u4e9b\uff0c\u81ea\u5df1\u7684\u773c\u775b\u5c31\u6703\u6fd5\u6f64\u8d77\u4f86\u3002</div>\n\n<div>\u4e3b\u554a\uff0c\u6211\u771f\u7684\u4e0d\u914d\u4f60\u7684\u611b\u3002</div>\n\n<div>&nbsp;</div>\n\n<div>&nbsp;</div>\n\n<div>\u5c31\u8b93\u5c0f\u5c0f\u7f8a\u7576\u96bb\u5fae\u4e0d\u8db3\u9053\u7684\u5c0f\u7f8a\u5427\uff1f</div>\n\n<div>\u8b93\u4e00\u5207\u7684\u7126\u9ede\uff0c\u90fd\u96c6\u4e2d\u5728\u90a3\u5927\u7267\u4eba\u8eab\u4e0a\u3002</div>\n\n<div>\u53ea\u6709\u7942\uff0c\u4e5f\u552f\u6709\u7942\uff0c\u624d\u914d\u5f97\u4e00\u5207\u69ae\u8000\u8207\u6ce8\u76ee\u3002</div>\n\n<div>\u5c0f\u5c0f\u7f8a\u505a\u7684\uff0c\u53ea\u662f\u7576\u500b\u5e36\u9818\u5927\u5bb6\u5c07\u76ee\u5149\u671d\u5411\u90a3\u7267\u8005\u7684\u4eba\u800c\u5df2\u3002</div>\n\n<div>&nbsp;</div>\n\n<div>&nbsp;</div>\n\n<div>\u552f\u7368\u6069\u5178\uff01</div>\n\n<div>\u552f\u7368\u69ae\u8000\u4e0a\u5e1d\uff01</div>\n\n<div>\u963f\u5011\u3002</div>\n\n<div>&nbsp;</div>\n\n<div>&nbsp;</div>\n\n<div>\u6700\u5f8c\uff0c\u9084\u662f\u8981\u63d0\u9192\u5927\u5bb6\u4e00\u4e0b\uff1a</div>\n\n<div>\u8acb\u9ad4\u8ad2\u4e00\u4e9b\u80a2\u9ad4\u3002\u4e0d\u7ba1\u662f\u8eab\u9ad4\u4e0a\u3001\u7cbe\u795e\u4e0a\u3001\u5fc3\u9748\u4e0a\u3002</div>\n\n<div>\uff5e\uff5e\uff5e\uff5e\uff5e\uff5e\uff5e\uff5e</div>\n\n<div>&nbsp;</div>\n\n<div>&nbsp;</div>\n\n<div>&nbsp;</div>\n\n<div>&nbsp;</div>\n\n<div>\uff5e\uff5e\uff5e\uff5e\uff5e\uff5e\uff5e\uff5e\uff5e\uff5e</div>\n\n<div>\u5c0f\u5c0f\u7f8a&nbsp; \u65bc 2007/10/22 23:19 \u516c\u958b\u56de\u8986</div>\n\n<div>\u7d66\u7121\u540d\u7db2\u53cb\uff1a</div>\n\n<div>\u9019\u662f\u6211\u6700\u5f8c\u4e00\u6b21\u56de\u7b54\u4f60\u4e86\u3002</div>\n\n<div>\u53ea\u8981\u518d\u4e00\u6b21\uff0c\u6211\u5c07\u5168\u9762\u522a\u9664\u4f60\u6240\u6709\u7684\u554f\u984c\u8207\u767c\u8a00\u3002</div>\n\n<div>&nbsp;</div>\n\n<div>&nbsp;</div>\n\n<div>\u6211\u662f\u4e0d\u662f\u7267\u5e2b\uff1f</div>\n\n<div>\u6211\u662f\u7267\u5e2b\uff0c\u6211\u7684\u6587\u7ae0\u6703\u70ba\u6211\u52a0\u5e7e\u5206\uff1f\u6e1b\u5e7e\u5206\uff1f</div>\n\n<div>\u6211\u7684\u8eab\u4efd\uff0c\u6703\u70ba\u6211\u7684\u6587\u7ae0\u52a0\u5e7e\u5206\uff0c\u6e1b\u5e7e\u5206\uff1f</div>\n\n<div>\u4f60\u662f\u4f86\u8b80\u5c0f\u5c0f\u7f8a\u7684\u6587\u7ae0\uff0c</div>\n\n<div>\u9084\u662f\u60f3\u8b80\u7267\u5e2b\u7684\u6587\u7ae0\u3001\u8001\u5e2b\u7684\u6587\u7ae0\u3001\u6559\u6388\u7684\u6587\u7ae0\u3001\u3001\u3001\uff1f</div>\n\n<div>\u5c0f\u5c0f\u7f8a\u5f1f\u5144\uff0c\u8b8a\u6210\u5c0f\u5c0f\u7f8a\u7267\u5e2b\u3001\u5c0f\u5c0f\u7f8a\u6559\u6388\u3001\u5c0f\u5c0f\u7f8a\u90e8\u9577\uff0c</div>\n\n<div>\u5c31\u6703\u4f7f\u5c0f\u5c0f\u7f8a\u7684\u6587\u7ae0\u771f\u7406\u6027\u5927\u589e\u55ce\uff1f</div>\n\n<div>&nbsp;</div>\n\n<div>&nbsp;</div>\n\n<div>\u6211\u66fe\u516c\u958b\u5728\u57fa\u7763\u6559\u7db2\u7ad9\u4e0a\u8b1b\u904e\u6211\u7684\u8eab\u4efd\uff0c</div>\n\n<div>\u76ee\u7684\u662f\u8981\u8868\u660e\u6211\u4e0d\u70ba\u540d\u3001\u4e0d\u70ba\u5229\u7684\u5fc3\u3002</div>\n\n<div>\u6c92\u60f3\u5230\uff0c\u7adf\u7136\u6709\u7db2\u53cb\u56e0\u6b64\u8a8d\u70ba\u6211\u662f\u5728\u70ab\u8000\u3002</div>\n\n<div>\u5f9e\u6b64\u4ee5\u5f8c\uff0c\u6211\u5c31\u9589\u53e3\u4e0d\u63d0\u6211\u7684\u8eab\u4efd\u3002</div>\n\n<div>\u6211\u4e0d\u9858\u7528\u81ea\u5df1\u7684\u8eab\u4efd\u3001\u5730\u4f4d\uff0c\u4f86\u70ba\u81ea\u5df1\u505a\u4efb\u4f55\u4e00\u5206\u70ab\u8000\u3002</div>\n\n<div>&nbsp;</div>\n\n<div>&nbsp;</div>\n\n<div>\u5c0f\u5c0f\u7f8a\uff0c\u5c31\u662f\u4e00\u500b\u7121\u540d\u7684\u5c0f\u5f1f\u5144\u3002</div>\n\n<div>\u5728\u4e3b\u88e1\uff0c\u6c92\u6709\u982d\u929c\u3001\u6c92\u6709\u5b78\u6b77\u3001\u6c92\u6709\u540d\u671b\u3001\u6c92\u6709\u5730\u4f4d\u3002</div>\n\n<div>\u5728\u9019\u5712\u5730\u88e1\uff0c\u6211\u6c92\u6709\u6bd4\u8ab0\u9ad8\u4eba\u4e00\u7b49\u3002</div>\n\n<div>\u6211\u8b1b\u7684\u8a71\uff0c\u4e0d\u662f\u56e0\u70ba\u6211\u7684\u8eab\u4efd\u3001\u5730\u4f4d\u3001\u5b78\u6b77\u3001\u3001\u3001\u624d\u8868\u793a\u6211\u6b63\u78ba\u3002</div>\n\n<div>\u6211\u8b1b\u7684\u8a71\u5982\u679c\u53ef\u4fe1\uff0c\u7d14\u7cb9\u662f\u56e0\u70ba\u6211\u8b1b\u7684\u662f\u5408\u8056\u7d93\u7684\u771f\u7406\uff0c\u5982\u6b64\u800c\u5df2\u3002</div>\n\n<div>&nbsp;</div>\n\n<div>&nbsp;</div>\n\n<div>\u800c\u6211\u5011\u9019\u88e1\u7684\u98a8\u683c\uff0c</div>\n\n<div>\u4e5f\u5f9e\u4f86\u4e0d\u6703\u56e0\u70ba\u767c\u8a00\u8005\u662f\u7267\u5e2b\u3001\u6559\u6388\u3001\u3001\u3001\u3001\uff0c\u5c31\u7279\u5225\u5c0a\u656c\u4f60\uff1b</div>\n\n<div>\u56e0\u70ba\u4f60\u662f\u5c0f\u5b78\u7562\u696d\u751f\u3001\u6728\u5320\u3001\u6e05\u9053\u592b\uff0c\u5c31\u770b\u4e0d\u8d77\u4f60\u3002</div>\n\n<div>\u5728\u6211\u5011\u9019\u88e1\uff0c\u81ea\u5df1\u80fd\u4e0d\u80fd\u88ab\u4eba\u5c0a\u656c\uff0c</div>\n\n<div>\u7d14\u7cb9\u662f\u56e0\u70ba\u81ea\u5df1\u8b1b\u7684\u5408\u4e0d\u5408\u771f\u7406\u3001\u5c0d\u5225\u4eba\u6709\u6c92\u6709\u9020\u5c31\u8207\u5e6b\u52a9\uff0c\u5982\u6b64\u800c\u5df2\u3002</div>\n\n<div>\u6709\u6642\uff0c\u6211\u6703\u56e0\u70ba\u67d0\u4e9b\u5f1f\u5144\u59d0\u59b9\u7684\u5b78\u7d93\u6b77\uff0c\u7279\u5225\u63a8\u85a6\u9019\u4e9b\u4eba\u7684\u6587\u7ae0\u3002</div>\n\n<div>\u9019\u662f\u56e0\u70ba\u4ed6\u5011\u767c\u8a00\u4e0d\u591a\uff0c\u70ba\u907f\u514d\u6709\u4eba\u8aa4\u5224\u6240\u81f4\u3002</div>\n\n<div>\u800c\u6211\u81ea\u5df1\uff0c\u7531\u65bc\u6587\u7ae0\u5df2\u7d93\u597d\u5e7e\u767e\u7bc7\uff0c\u55ae\u55ae\u5f9e\u6211\u7684\u6587\u7ae0\u5c31\u8db3\u4ee5\u5224\u65b7\u53ef\u4fe1\u5ea6\u3002</div>\n\n<div>&nbsp;</div>\n\n<div>&nbsp;</div>\n\n<div>\u6211\u5728\u9019\u88e1\uff0c\u8981\u5f88\u56b4\u53b2\u7684\u8b1b\uff1a</div>\n\n<div>\u6211\u5c0d\u9019\u8a71\u984c\u57282007\u5e7410\u670822\u65e5 17:13\u767c\u8868\u7684\u5f88\u9577\u7684\u56de\u61c9\uff0c</div>\n\n<div>\u5982\u679c\u4e0d\u80fd\u4f7f\u60a8\u5c07\u6ce8\u610f\u529b\u5f9e\u6211\u8eab\u4e0a\u79fb\u8f49\u5230\u771f\u7406\u8eab\u4e0a\uff0c</div>\n\n<div>\u90a3\u6211\u6703\u8a8d\u70ba\u4f60\u5c0d\u771f\u7406\u6c92\u8208\u8da3\uff0c\u4e0d\u503c\u5f97\u6211\u6d6a\u8cbb\u6642\u9593\u3002</div>\n\n<div>&nbsp;</div>\n\n<div>&nbsp;</div>\n\n<div>\u600e\u9ebc\u6709\u6642\u9593\u7ba1\u7406\u9019\u90e8\u843d\u683c\uff1f</div>\n\n<div>\u300e\u4e5f\u7528\u4e0d\u8457\u8ab0\u898b\u8b49\u4eba\u600e\u6a23\uff0c\u56e0\u4ed6\u77e5\u9053\u4eba\u5fc3\u88e1\u6240\u5b58\u7684\u300f\uff08\u7d042\uff1a25\uff09</div>\n\n<div>&nbsp;</div>\n\n<div>&nbsp;</div>\n\n<div>\u95dc\u65bc\u6211\u81ea\u5df1\u7684\u90e8\u5206\uff0c\u6bcf\u591a\u8b1b\u4e00\u4e9b\uff0c\u5c31\u8b8a\u6210\u597d\u50cf\u5728\u70ab\u8000\u81ea\u5df1\u7684\u4e00\u5207\u3002</div>\n\n<div>\u5509\uff01</div>\n\n<div>\u6211\u8981\u642c\u51fa\u982d\u929c\u548c\u5b78\u7d93\u6b77\uff0c\u6240\u82b1\u7684\u6642\u9593\u8207\u5fc3\u529b\uff0c\u771f\u80fd\u8b93\u4eba\u66f4\u8a8d\u8b58\u4e3b\u55ce\uff1f</div>\n\n<div>\u6240\u4ee5\uff0c\u5225\u518d\u8981\u6211\u6d6a\u8cbb\u6642\u9593\u53bb\u89e3\u91cb\u9019\u4e00\u4e9b\u4e86\u3002</div>\n\n<div>&nbsp;</div>\n\n<div>&nbsp;</div>\n\n<div>\u6240\u6709\u5c0d\u6211\u500b\u4eba\u6709\u8208\u8da3\u7684\uff0c\u6211\u5728\u5929\u4e0a\u6703\u6709\u5f88\u591a\u6642\u9593\u56de\u7b54\u5927\u5bb6\u3002</div>\n\n<div>\u591a\u554f\u4e9b\u4fe1\u4ef0\u554f\u984c\uff0c\u6bd4\u8f03\u5be6\u969b\u3002</div>\n\n<div>\u4e0d\u8981\u518d\u4f86\u554f\u6211\u500b\u4eba\u6709\u95dc\u7684\u554f\u984c\u4e86\u3002</div>\n\n<div>&nbsp;</div>\n\n<div>&nbsp;</div>\n\n<div>&nbsp;</div>\n\n<div>&nbsp;</div>\n\n<div>\uff5e\uff5e\uff5e\uff5e\uff5e\uff5e\uff5e</div>\n\n<div>\u5c0f\u5c0f\u7f8a \u65bc 2007/10/22 23:42 \u516c\u958b\u56de\u8986</div>\n\n<div>\u7d66PETER\uff1a</div>\n\n<div>\u525b\u597d\u9019\u4e00\u3001\u4e8c\u661f\u671f\uff0c\u5c31\u6709\u4e00\u4f4d\u5c6c\u540d\u6c6a\u5f1f\u5144\u7684\u4f86\u904e\u6211\u5011\u9019\u88e1\u767c\u8a00\u3002</div>\n\n<div>\u8aa4\u5224\u4e4b\u8655\uff0c\u5c1a\u8acb\u898b\u8ad2\u3002</div>\n\n<div>&nbsp;</div>\n\n<div>&nbsp;</div>\n\n<div>\u4f46\u4e5f\u8d81\u6a5f\u8b93\u6211\u5c0d\u60a8\u505a\u500b\u63d0\u9192\uff1a</div>\n\n<div>\u65e2\u7136\u60a8\u4f86\u9019\u88e1\u6642\u9593\u90a3\u9ebc\u77ed\uff0c\u70ba\u4ec0\u9ebc\u4e0d\u82b1\u6642\u9593\u591a\u95b1\u8b80\u88e1\u9762\u7684\u6587\u7ae0\u518d\u8aaa\u5462\uff1f</div>\n\n<div>\u60a8\u4e0d\u89ba\u5f97\uff0c\u525b\u4f86\u9019\u88e1\u4f5c\u5ba2\uff0c\u5c31\u8981\u6c42\u4e3b\u4eba\u8981\u7528\u771f\u5be6\u59d3\u540d\uff0c\u6703\u4e0d\u6703\u6709\u9ede\u4e0d\u79ae\u8c8c\uff1f</div>\n\n<div>\u9023\u5ba2\u4eba\u81ea\u5df1\u90fd\u6c92\u7528\u771f\u5be6\u59d3\u540d\u4f86\u4f5c\u5ba2\u4e86\uff0c</div>\n\n<div>\u70ba\u4ec0\u9ebc\u6703\u89ba\u5f97\u81ea\u5df1\u6709\u6b0a\u5229\u8981\u6c42\u4e3b\u4eba\u5fc5\u9808\u9019\u6a23\u505a\u5462\uff1f</div>\n\n<div>\u4e3b\u4eba\u6709\u56e0\u70ba\u54ea\u500b\u5ba2\u4eba\u6c92\u7528\u771f\u5be6\u59d3\u540d\u767c\u8a00\uff0c\u5c31\u4e0b\u9010\u5ba2\u4ee4\u55ce\uff1f</div>\n\n<div>\u5ba2\u4eba\u85c9\u8457\u4e3b\u4eba\u7684\u5bec\u5bb9\uff0c\u53cd\u904e\u4f86\u82db\u6c42\u4e3b\u4eba\uff0c\u9019\u771f\u7684\u5f88\u4e0d\u79ae\u8c8c\u3002</div>\n\n<div>&nbsp;</div>\n\n<div>&nbsp;</div>\n\n<div>\u5c0d\u4e3b\u4eba\u500b\u4eba\u6709\u8208\u8da3\uff0c\u591a\u8b80\u6587\u7ae0\uff0c\u81ea\u6703\u6709\u500b\u5224\u65b7\u51fa\u4f86\u3002</div>\n\n<div>\u4f46\u5f88\u4e0d\u5e78\u7684\uff0c\u60a8\u8b80\u6211\u7684\u6587\u7ae0\uff0c\u537b\u6703\u5224\u65b7\u51fa\u6211\u662f\u59ca\u59b9\uff0c</div>\n\n<div>\u9019\u8868\u793a\u5224\u65b7\u7684\u529f\u529b\u9084\u6709\u5f85\u52a0\u5f37\u3002</div>\n\n<div>\u5f88\u591a\u5f1f\u5144\u59d0\u59b9\u55ae\u6191\u6211\u7684\u6587\u7ae0\uff0c\u5c31\u90fd\u5f88\u6b63\u78ba\u5224\u65b7\u51fa\u6211\u662f\u5f1f\u5144\uff0c\u4f46\u60a8\u537b\u8aa4\u5224\u3002</div>\n\n<div>\u6240\u4ee5\uff0c\u66ab\u6642\u8acb\u60a8\u5148\u591a\u8b80\u3001\u591a\u807d\u3001\u591a\u770b\uff0c</div>\n\n<div>\u4e0d\u9700\u6025\u8457\u767c\u8a00\u3001\u66f4\u4e0d\u9700\u6025\u8457\u8981\u6c42\u6211\u8a72\u505a\u4e9b\u4ec0\u9ebc\u3002</div>\n\n<div>&nbsp;</div>\n\n<div>&nbsp;</div>\n\n<div>\u6709\u4fe1\u4ef0\u4e0a\u7684\u7591\u554f\uff0c\u96a8\u6642\u6b61\u8fce\u767c\u554f\u3002</div>\n\n<div>\u6b63\u5982\u7591\u60d1\u7db2\u53cb\u6240\u8aaa\u7684\u4e00\u6a23\u3002</div>\n\n<div>\u6211\u5011\u9019\u88e1\uff0c\u4e00\u8cab\u4ee5\u4f86\uff0c\u90fd\u5f88\u52aa\u529b\u5e6b\u52a9\u6709\u4fe1\u4ef0\u7591\u554f\u7684\u5f1f\u5144\u59ca\u59b9\u89e3\u6c7a\u554f\u984c\u3002</div>\n\n<div>&nbsp;</div>\n\n<div>&nbsp;</div>\n\n<div>\u81f3\u65bc\u5c0d\u6211\u500b\u4eba\u7684\u8208\u8da3\uff0c\u5c31\u514d\u4e86\u3002</div>\n\n<div>&nbsp;</div>\n\n<div>&nbsp;</div>\n\n<div>\u6211\u5c0d\u9019\u7bc7\u8a71\u984c\u7684\u56de\u61c9\uff0c\u5230\u6b64\u70ba\u6b62\uff0c</div>\n\n<div>\u672a\u4f86\u4e0d\u518d\u5c0d\u6b64\u8a71\u984c\u63d0\u51fa\u56de\u61c9\u3002</div>\n\n<div>\u751f\u547d\u6709\u9650\uff0c\u6211\u9084\u6709\u66f4\u591a\u6709\u610f\u7fa9\u7684\u4e8b\u7b49\u8457\u53bb\u505a\u3002</div>\n\n<div>\u9858\u4e0a\u5e1d\u795d\u798f\u5927\u5bb6\u3002</div>\n\n<p>&nbsp;</p>\n\n<p>\u5c0f\u5c0f\u7f8a</p>\n\n<p>&nbsp;</p>\n", "images": [], "first_published_at": "1718268569"}